satvatsagarml/1.py
satvatsagarml/10.py
satvatsagarml/11.py
satvatsagarml/12.py
satvatsagarml/13.py
satvatsagarml/2.py
satvatsagarml/3.py
satvatsagarml/4.py
satvatsagarml/5.py
satvatsagarml/6.py
satvatsagarml/7.py
satvatsagarml/8.py
satvatsagarml/9.py
satvatsagarml/__init__.py
satvatsagarml-2.1.dist-info/METADATA
satvatsagarml-2.1.dist-info/WHEEL
satvatsagarml-2.1.dist-info/top_level.txt
satvatsagarml-2.1.dist-info/RECORD
